{
    "semana": {
        "numero": 25,
        "fecha_inicio": "22/06/26",
        "fecha_fin": "28/06/26"
    },
    "clave_obra": "C-424",
    "nombre_obra": "URBANIZACIÓN MASTER",
    "direccion_obra": "TLAJOMULCO",
    "cuadrillas": [
        {
            "numero": null,
            "tipo": "dia",
            "trabajadores": [
                {
                    "clave": 1201,
                    "nombre": "FLORES OROPEZA ENRIQUE",
                    "puesto": "OF",
                    "salario_diario": 638.8,
                    "dias": 7.0,
                    "numero_cuadrilla": 1,
                    "horas_extras": "",
                    "descripcion_horas_extras": "",
                    "ponderacion": 0,
                    "puntos": 0,
                    "porcentaje": 0
                }
            ],
            "subtitulos": [],
            "conceptos": [],
            "actividades": ""
        }
    ]
}