{
    "semana": {
        "numero": 25,
        "fecha_inicio": "22/06/26",
        "fecha_fin": "28/06/26"
    },
    "clave_obra": "ID-1079",
    "nombre_obra": "NAVES PARQUE EMAR",
    "direccion_obra": "CARRETERA A TESISTÁN SAN CRISTOBAL DE LA BARRANCA",
    "cuadrillas": [
        {
            "numero": 1,
            "tipo": "destajo",
            "trabajadores": [
                {
                    "clave": 1201,
                    "nombre": "FLORES OROPEZA ENRIQUE",
                    "puesto": "OF",
                    "salario_diario": 638.8,
                    "dias": 6.0,
                    "numero_cuadrilla": 1,
                    "horas_extras": "",
                    "descripcion_horas_extras": "",
                    "ponderacion": 60,
                    "puntos": 360.0,
                    "porcentaje": 60.0
                },
                {
                    "clave": 1990,
                    "nombre": "GUARDADO SÁNCHEZ MARTÍN",
                    "puesto": "PEON",
                    "salario_diario": 354.88,
                    "dias": 6.0,
                    "numero_cuadrilla": 1,
                    "horas_extras": "",
                    "descripcion_horas_extras": "",
                    "ponderacion": 40,
                    "puntos": 240.0,
                    "porcentaje": 40.0
                }
            ],
            "subtitulos": [
                {
                    "nombre": "GENERALES",
                    "conceptos": [
                        {
                            "clave": "lote10",
                            "descripcion": "Lote",
                            "unidad": "LOTE",
                            "largo": "",
                            "ancho": "",
                            "alto": "",
                            "piezas": "8.03495",
                            "notas": "UNA CANTIDAD GRANDE DE ACTIVIDADES, LIMPIEZA, RETIRAR ESCOMBRO, RECOGER MADERA. CHATARRA, MONTENES, BASURA, CRISTALES ROTOS, BODEGUERO , ENTREGA Y RECEPCION DE MATERIALES."
                        }
                    ]
                }
            ],
            "conceptos": [],
            "actividades": ""
        }
    ]
}